LibLynx-0.17.data/data/LICENSE
liblynx/__init__.py
liblynx/django.py
liblynx/starlette.py
LibLynx-0.17.dist-info/LICENSE
LibLynx-0.17.dist-info/METADATA
LibLynx-0.17.dist-info/WHEEL
LibLynx-0.17.dist-info/top_level.txt
LibLynx-0.17.dist-info/RECORD
