Metadata-Version: 2.1
Name: LibLynx
Version: 0.17
Summary: Python Library to interact with LibLynx
Home-page: https://gitlab.com/brillpublishers/code/liblynx
Author: Etienne Posthumus
Author-email: posthumus@brill.com
License: MIT
Platform: UNKNOWN
Classifier: Programming Language :: Python :: 3
Classifier: License :: OSI Approved :: MIT License
Classifier: Operating System :: OS Independent
License-File: LICENSE
Requires-Dist: requests
Requires-Dist: pyjwt (~=1.7)
Provides-Extra: django
Requires-Dist: django ; extra == 'django'
